streamsights_api/__init__.py
streamsights_api/logic.py
STREAMSIGHTS-0.1.dist-info/METADATA
STREAMSIGHTS-0.1.dist-info/WHEEL
STREAMSIGHTS-0.1.dist-info/top_level.txt
STREAMSIGHTS-0.1.dist-info/RECORD
