Metadata-Version: 2.1
Name: STREAMSIGHTS
Version: 0.1
Summary: API package that provides us the method to add the user data from the API
Author: dinesh
Author-email: dineshsugumar289@gmail.com
License: MIT
Requires-Dist: pandas
Requires-Dist: requests
